dava_explorer/_version.py
dava_explorer/country_indicators.csv
dava_explorer/dava.py
dava_explorer/dava_test.py
dava_explorer-0.0.4.dist-info/LICENSE
dava_explorer-0.0.4.dist-info/METADATA
dava_explorer-0.0.4.dist-info/WHEEL
dava_explorer-0.0.4.dist-info/top_level.txt
dava_explorer-0.0.4.dist-info/RECORD
