Metadata-Version: 2.1
Name: dava_explorer
Version: 0.0.4
Author: David Kuchelmeister
Requires-Python: >=3.13
License-File: LICENSE
Requires-Dist: dash>=2.18.2
Provides-Extra: dev
Requires-Dist: pytest; extra == "dev"
Requires-Dist: tox; extra == "dev"
Requires-Dist: coverage; extra == "dev"
Requires-Dist: flake8; extra == "dev"
Requires-Dist: pre-commit; extra == "dev"
Requires-Dist: mypy; extra == "dev"
Requires-Dist: black; extra == "dev"
Requires-Dist: ruff; extra == "dev"
Requires-Dist: daves_utilities; extra == "dev"
Requires-Dist: setuptools_scm; extra == "dev"
Requires-Dist: twine; extra == "dev"
Requires-Dist: uv; extra == "dev"
Requires-Dist: pre-commit; extra == "dev"
Requires-Dist: pre-commit-hooks; extra == "dev"
Requires-Dist: reorder-python-imports; extra == "dev"
